segment_image/__init__.py
segment_image/gvf_snake.py
segment_image/k_means.py
segment_image/gvf_snake_lib/__init__.py
segment_image/gvf_snake_lib/gradient_descent_base.py
segment_image/gvf_snake_lib/gvf.py
segment_image/gvf_snake_lib/snake.py
segment_image/gvf_snake_lib/utils/__init__.py
segment_image/gvf_snake_lib/utils/display.py
segment_image-0.0.3.dist-info/LICENSE
segment_image-0.0.3.dist-info/METADATA
segment_image-0.0.3.dist-info/WHEEL
segment_image-0.0.3.dist-info/top_level.txt
segment_image-0.0.3.dist-info/RECORD
