Metadata-Version: 2.1
Name: segment-image
Version: 0.0.3
Summary: A package used to segment an image
Home-page: https://github.com/MyDuan/segment_image
Author: yu.duan
Author-email: dy1226130575@163.com
License: UNKNOWN
Project-URL: Bug Tracker, https://github.com/MyDuan/segment_image/issues
Platform: UNKNOWN
Classifier: Programming Language :: Python :: 3
Classifier: License :: OSI Approved :: MIT License
Classifier: Operating System :: OS Independent
Requires-Python: >=3.6
License-File: LICENSE
